<?xml version="1.0"?>
<opencv_storage>
<stage4>
  <maxWeakCount>3</maxWeakCount>
  <stageThreshold>9.9783480167388916e-01</stageThreshold>
  <weakClassifiers>
    <_>
      <internalNodes>
        0 -1 121241 -7.8606797615066171e-04</internalNodes>
      <leafValues>
        -6.6666668653488159e-01 9.1452991962432861e-01</leafValues></_>
    <_>
      <internalNodes>
        0 -1 44115 -5.1721170544624329e-02</internalNodes>
      <leafValues>
        -8.9546662569046021e-01 8.7932258844375610e-01</leafValues></_>
    <_>
      <internalNodes>
        0 -1 10663 -2.4633831344544888e-03</internalNodes>
      <leafValues>
        9.7877150774002075e-01 -6.9907867908477783e-01</leafValues></_></weakClassifiers></stage4>
</opencv_storage>
